[
  {
    "type": "nav_link",
    "title": "skip-link main",
    "elementID": "blz-nav-skip-link-main",
    "slot": "skip-link",
    "blzModalTrigger": "",
    "text": "Skip to Main Content",
    "subtext": "",
    "badge": "",
    "icon": "",
    "iconSize": "",
    "href": "#main",
    "isMobileGame": false,
    "isExternal": false,
    "variant": "",
    "eventLabel": "skip-link-main",
    "hideOnDesktop": false,
    "hideOnMobile": false
  },
  {
    "type": "nav_link",
    "title": "ow2 - skip-link footer",
    "elementID": "blz-nav-skip-link-footer",
    "slot": "skip-link",
    "blzDevice": "",
    "blzModalTrigger": "",
    "text": "Skip to Footer Content",
    "subtext": "",
    "badge": "",
    "icon": "",
    "iconSize": "",
    "href": "#Page-footer",
    "isMobileGame": false,
    "isExternal": false,
    "variant": "",
    "eventLabel": "skip-link-footer",
    "hideOnDesktop": false,
    "hideOnMobile": false,
    "requiresAuthentication": false
  },
  {
    "type": "nav_link",
    "title": "ow2 - Mobile Site Logo",
    "elementID": "blz-nav-ow2-mobile-site-logo",
    "slot": "mobile-site-logo",
    "blzModalTrigger": "",
    "text": "",
    "subtext": "",
    "badge": "",
    "icon": "",
    "iconSrc": "https://blz-contentstack-images.akamaized.net/v3/assets/blt72f16e066f85e164/bltbff81ca0eea80f49/697d0acef50df33bc74693e1/rebrand_logo.png",
    "iconSize": "",
    "href": "/",
    "isMobileGame": false,
    "isExternal": false,
    "variant": "",
    "eventLabel": "mobile-logo",
    "hideOnDesktop": false,
    "hideOnMobile": false,
    "requiresAuthentication": false
  },
  {
    "type": "nav_link",
    "title": "ow2 - Site Icon",
    "elementID": "blz-nav-ow2-site-icon",
    "slot": "site-icon",
    "blzDevice": "",
    "blzModalTrigger": "",
    "text": "Overwatch",
    "subtext": "",
    "badge": "",
    "icon": "overwatch-2-dark",
    "iconSize": "",
    "href": "/",
    "isMobileGame": false,
    "isExternal": false,
    "classes": "icon-only",
    "variant": "icon-only",
    "eventLabel": "game_logo",
    "hideOnDesktop": false,
    "hideOnMobile": false,
    "requiresAuthentication": false
  },
  {
    "type": "nav_dropdown",
    "title": "ow2 - blizzard",
    "elementID": "blz-nav-ow-blizz-dropdown",
    "slot": "site-logo",
    "blzDevice": "",
    "text": "",
    "badge": "",
    "icon": "blizzard",
    "href": "http://www.blizzard.com",
    "variant": "",
    "links": [
      {
        "title": "More From Blizzard (title)",
        "elementID": "blz-nav-more-from-blizzard-title",
        "slot": "dropdown-primary-menu",
        "blzModalTrigger": "",
        "text": "More From Blizzard",
        "subtext": "",
        "badge": "",
        "icon": "",
        "iconSize": "",
        "href": "",
        "isMobileGame": false,
        "isExternal": false,
        "classes": "title",
        "variant": "title",
        "eventLabel": "other",
        "ctaPlacement": "other",
        "hideOnDesktop": true,
        "hideOnMobile": false
      },
      {
        "title": "Visit Blizzard (logo dropdown)",
        "elementID": "blz-nav-visit-blizzard-dropdown",
        "slot": "dropdown-primary-menu",
        "blzModalTrigger": "",
        "text": "Visit Blizzard.com",
        "subtext": "",
        "badge": "",
        "icon": "employee",
        "iconSize": "300",
        "href": "https://www.blizzard.com",
        "isMobileGame": false,
        "isExternal": false,
        "variant": "",
        "eventLabel": "Visit Blizzard",
        "ctaPlacement": "Mobile Menu",
        "hideOnDesktop": false,
        "hideOnMobile": false
      },
      {
        "title": "All Games (logo dropdown)",
        "elementID": "blz-nav-visit-blizzard-dropdown-2",
        "slot": "dropdown-primary-menu",
        "blzModalTrigger": "",
        "text": "All Games",
        "subtext": "",
        "badge": "",
        "icon": "grid",
        "iconSize": "300",
        "href": "https://www.blizzard.com/games",
        "isMobileGame": false,
        "isExternal": false,
        "variant": "",
        "eventLabel": "Visit Blizzard",
        "ctaPlacement": "Mobile Menu",
        "hideOnDesktop": false,
        "hideOnMobile": false
      },
      {
        "title": "You Might Also Like (title)",
        "elementID": "blz-nav-you-might-also-like-title",
        "slot": "dropdown-secondary-menu",
        "blzModalTrigger": "",
        "text": "You Might Also Like",
        "subtext": "",
        "badge": "",
        "icon": "",
        "iconSize": "",
        "href": "",
        "isMobileGame": false,
        "isExternal": false,
        "classes": "title",
        "variant": "title",
        "eventLabel": "other",
        "ctaPlacement": "other",
        "hideOnDesktop": false,
        "hideOnMobile": false
      },
      {
        "title": "Diablo IV",
        "elementID": "blz-nav-diablo-IV",
        "slot": "dropdown-secondary-menu",
        "blzModalTrigger": "",
        "text": "Diablo IV",
        "subtext": "Action RPG",
        "badge": "",
        "icon": "diablo-IV",
        "iconSize": "",
        "href": "https://diablo4.blizzard.com",
        "isMobileGame": false,
        "isExternal": false,
        "classes": "jumbo",
        "variant": "jumbo",
        "eventLabel": "Diablo IV",
        "ctaPlacement": "Related Games",
        "hideOnDesktop": false,
        "hideOnMobile": false,
        "requiresAuthentication": false
      },
      {
        "title": "World of Warcraft",
        "elementID": "blz-nav-wow",
        "slot": "dropdown-secondary-menu",
        "blzModalTrigger": "",
        "text": "World of Warcraft",
        "subtext": "MMORPG",
        "badge": "",
        "icon": "world-of-warcraft",
        "iconSize": "",
        "href": "https://worldofwarcraft.blizzard.com",
        "isMobileGame": false,
        "isExternal": false,
        "classes": "jumbo",
        "variant": "jumbo",
        "eventLabel": "World of Warcraft",
        "ctaPlacement": "Related Games",
        "hideOnDesktop": false,
        "hideOnMobile": false,
        "requiresAuthentication": false
      },
      {
        "title": "Kazoo",
        "elementID": "blz-nav-kazoo",
        "slot": "dropdown-secondary-menu",
        "blzDevice": "",
        "blzModalTrigger": "",
        "text": "World of Warcraft: Mists of Pandaria Classic",
        "subtext": "Expansion",
        "badge": "",
        "icon": "",
        "iconSrc": "https://blz-contentstack-images.akamaized.net/v3/assets/blt72f16e066f85e164/blt832a991c0f0b33ec/687806c49c5ca9b6991dcad6/game_icon_mists_classic.svg",
        "iconSize": "",
        "href": "https://wowclassic.blizzard.com",
        "isMobileGame": false,
        "isExternal": false,
        "classes": "jumbo",
        "variant": "jumbo",
        "eventLabel": "Kazoo",
        "ctaPlacement": "Related Games",
        "hideOnDesktop": false,
        "hideOnMobile": false,
        "requiresAuthentication": false
      },
      {
        "title": "Hearthstone",
        "elementID": "blz-nav-hs",
        "slot": "dropdown-secondary-menu",
        "blzDevice": "",
        "blzModalTrigger": "",
        "text": "Hearthstone",
        "subtext": "Strategy Card Game",
        "badge": "",
        "icon": "hearthstone",
        "iconSize": "",
        "href": "https://hearthstone.blizzard.com/",
        "isMobileGame": false,
        "isExternal": false,
        "classes": "jumbo",
        "variant": "jumbo",
        "eventLabel": "Hearthstone",
        "hideOnDesktop": false,
        "hideOnMobile": false,
        "requiresAuthentication": false
      }
    ],
    "submenuHeading": "",
    "hideOnDesktop": false,
    "hideOnMobile": false,
    "requiresAuthentication": false
  },
  {
    "type": "nav_dropdown",
    "title": "ow2 - Game Info",
    "elementID": "blz-nav-ow2-nav-dropdown-game-info",
    "slot": "primary-menu",
    "blzDevice": "",
    "text": "Game Info",
    "badge": "New",
    "icon": "",
    "href": "",
    "variant": "",
    "links": [
      {
        "title": "ow2 - Videos",
        "elementID": "blz-nav-ow2-nav-link-videos",
        "slot": "dropdown-primary-menu",
        "blzDevice": "",
        "blzModalTrigger": "",
        "text": "Videos",
        "subtext": "",
        "badge": "",
        "icon": "",
        "iconSize": "",
        "href": "/videos",
        "isMobileGame": false,
        "isExternal": false,
        "variant": "",
        "eventLabel": "videos",
        "hideOnDesktop": false,
        "hideOnMobile": false,
        "requiresAuthentication": false
      },
      {
        "title": "ow2 - Game Info - Media",
        "elementID": "blz-nav-ow2-nav-link-game-info-media",
        "slot": "dropdown-primary-menu",
        "blzModalTrigger": "",
        "text": "Media",
        "subtext": "",
        "badge": "",
        "icon": "",
        "iconSize": "",
        "href": "/media",
        "isMobileGame": false,
        "isExternal": false,
        "variant": "",
        "eventLabel": "game-info-media",
        "hideOnDesktop": false,
        "hideOnMobile": false
      },
      {
        "title": "ow2 - Game Info - patch notes",
        "elementID": "blz-nav-ow2-nav-link-game-info-patch-notes",
        "slot": "dropdown-primary-menu",
        "blzModalTrigger": "",
        "text": "Patch Notes",
        "subtext": "",
        "badge": "",
        "icon": "",
        "iconSize": "",
        "href": "/news/patch-notes",
        "isMobileGame": false,
        "isExternal": false,
        "variant": "",
        "eventLabel": "game-info-patch-notes",
        "hideOnDesktop": false,
        "hideOnMobile": false
      },
      {
        "title": "ow2 - Stadium",
        "elementID": "blz-nav-ow2-nav-link-game-info-stadium",
        "slot": "dropdown-primary-menu",
        "blzDevice": "",
        "blzModalTrigger": "",
        "text": "Stadium",
        "subtext": "",
        "badge": "New",
        "icon": "",
        "iconSize": "",
        "href": "/stadium",
        "isMobileGame": false,
        "isExternal": false,
        "variant": "",
        "eventLabel": "game-info-stadium",
        "hideOnDesktop": false,
        "hideOnMobile": false,
        "requiresAuthentication": false
      }
    ],
    "submenuHeading": "",
    "hideOnDesktop": false,
    "hideOnMobile": false,
    "requiresAuthentication": false
  },
  {
    "type": "nav_link",
    "title": "ow2 - Heroes",
    "elementID": "blz-nav-ow2-nav-link-heroes",
    "slot": "primary-menu",
    "blzModalTrigger": "",
    "text": "Heroes",
    "subtext": "",
    "badge": "",
    "icon": "",
    "iconSize": "",
    "href": "/heroes",
    "isMobileGame": false,
    "isExternal": false,
    "variant": "",
    "eventLabel": "heroes",
    "hideOnDesktop": false,
    "hideOnMobile": false
  },
  {
    "type": "nav_link",
    "title": "ow2 - Season 2025",
    "elementID": "blz-nav-ow2-nav-link-season-overwatch-2025",
    "slot": "primary-menu",
    "blzDevice": "",
    "blzModalTrigger": "",
    "text": "Season",
    "subtext": "",
    "badge": "",
    "icon": "",
    "iconSize": "",
    "href": "/news/24246206/",
    "isMobileGame": false,
    "isExternal": false,
    "variant": "",
    "eventLabel": "season",
    "hideOnDesktop": false,
    "hideOnMobile": false,
    "requiresAuthentication": false
  },
  {
    "type": "nav_link",
    "title": "ow2 - News",
    "elementID": "blz-nav-ow2-news-nav-link",
    "slot": "primary-menu",
    "blzModalTrigger": "",
    "text": "News",
    "subtext": "",
    "badge": "",
    "icon": "",
    "iconSize": "",
    "href": "/news",
    "isMobileGame": false,
    "isExternal": false,
    "variant": "",
    "eventLabel": "news",
    "hideOnDesktop": false,
    "hideOnMobile": false
  },
  {
    "type": "nav_dropdown",
    "title": "ow2 - Community",
    "elementID": "blz-nav-ow2-nav-dropdown-community",
    "slot": "primary-menu",
    "blzDevice": "",
    "text": "Community",
    "badge": "",
    "icon": "",
    "href": "",
    "variant": "",
    "links": [
      {
        "title": "ow2 - Community - Forums",
        "elementID": "blz-nav-ow2-nav-link-community-forums",
        "slot": "dropdown-primary-menu",
        "blzModalTrigger": "",
        "text": "Forums",
        "subtext": "",
        "badge": "",
        "icon": "",
        "iconSize": "",
        "href": "https://us.forums.blizzard.com/en/overwatch/",
        "isMobileGame": false,
        "isExternal": false,
        "variant": "",
        "eventLabel": "community-forums",
        "hideOnDesktop": false,
        "hideOnMobile": false
      },
      {
        "title": "ow2 - Community - Hero Stats",
        "elementID": "blz-nav-ow2-nav-link-hero-stats",
        "slot": "dropdown-primary-menu",
        "blzDevice": "",
        "blzModalTrigger": "",
        "text": "Hero Stats",
        "subtext": "",
        "badge": "New",
        "icon": "",
        "iconSize": "",
        "href": "/rates",
        "isMobileGame": false,
        "isExternal": false,
        "variant": "",
        "eventLabel": "herostats",
        "hideOnDesktop": false,
        "hideOnMobile": false,
        "requiresAuthentication": false
      },
      {
        "title": "ow2 - Community - Player Profiles",
        "elementID": "blz-nav-ow2-nav-link-community-player-profiles",
        "slot": "dropdown-primary-menu",
        "blzModalTrigger": "",
        "text": "Player Profiles",
        "subtext": "",
        "badge": "",
        "icon": "",
        "iconSize": "",
        "href": "/search",
        "isMobileGame": false,
        "isExternal": false,
        "variant": "",
        "eventLabel": "community-player-profiles",
        "hideOnDesktop": false,
        "hideOnMobile": false
      },
      {
        "title": "ow2 - Community - Overwatch Esports",
        "elementID": "blz-nav-ow2-nav-link-community-overwatch-esports",
        "slot": "dropdown-secondary-menu",
        "blzDevice": "",
        "blzModalTrigger": "",
        "text": "Overwatch Esports",
        "subtext": "",
        "badge": "",
        "icon": "",
        "iconSize": "",
        "href": " https://esports.overwatch.com/",
        "isMobileGame": false,
        "isExternal": false,
        "variant": "",
        "eventLabel": "community-the-future-of-overwatch-esports",
        "hideOnDesktop": false,
        "hideOnMobile": false,
        "requiresAuthentication": false
      }
    ],
    "submenuHeading": "ESPORTS",
    "hideOnDesktop": false,
    "hideOnMobile": false,
    "requiresAuthentication": false
  },
  {
    "type": "nav_dropdown",
    "title": "ow2 - Shop",
    "elementID": "blz-nav-ow2-nav-dropdown-shop",
    "slot": "primary-menu",
    "text": "Shop",
    "badge": "",
    "icon": "",
    "href": "",
    "variant": "",
    "links": [
      {
        "title": "ow2-site - shop - in-game content",
        "elementID": "blz-nav-ow2-shop-ingame-content",
        "slot": "dropdown-primary-menu",
        "blzModalTrigger": "",
        "text": "In-Game Content",
        "subtext": "Battle Pass, Hero Skins, ...",
        "badge": "",
        "icon": "",
        "iconSrc": "https://blz-contentstack-images.akamaized.net/v3/assets/blt72f16e066f85e164/blt7554c198826502a5/659f3322d0868455a7bc0cdd/Overwatch_shop_icon_rounded.png",
        "iconSize": "",
        "href": "https://shop.battle.net/family/overwatch",
        "isMobileGame": false,
        "isExternal": false,
        "classes": "icon-rounded jumbo",
        "variant": "icon-rounded jumbo",
        "eventLabel": "in-game content",
        "hideOnDesktop": false,
        "hideOnMobile": false,
        "requiresAuthentication": false
      },
      {
        "title": "ow2 - Shop - Gear",
        "elementID": "blz-nav-ow2-nav-link-shop-gear",
        "slot": "dropdown-secondary-menu",
        "blzModalTrigger": "",
        "text": "Gear",
        "subtext": "",
        "badge": "",
        "icon": "",
        "iconSize": "",
        "href": "https://gear.blizzard.com/collections/overwatch",
        "isMobileGame": false,
        "isExternal": true,
        "variant": "",
        "eventLabel": "gear",
        "ctaPlacement": "",
        "event": "click_header_nav",
        "hideOnDesktop": false,
        "hideOnMobile": false
      }
    ],
    "submenuHeading": "",
    "hideOnDesktop": false,
    "hideOnMobile": false,
    "requiresAuthentication": false
  },
  {
    "type": "nav_dropdown",
    "title": "ow2 - Overflow",
    "elementID": "blz-nav-ow2-nav-link-overflow",
    "slot": "overflow",
    "text": "",
    "badge": "",
    "icon": "",
    "href": "",
    "variant": "",
    "links": [],
    "submenuHeading": "",
    "hideOnDesktop": false,
    "hideOnMobile": false
  },
  {
    "type": "nav_link",
    "title": "ow2-site - career profile",
    "elementID": "blz-nav-ow2-career-profile",
    "slot": "account-primary-top",
    "blzModalTrigger": "",
    "text": "Overwatch Profile",
    "subtext": "",
    "badge": "",
    "icon": "user-circle",
    "iconSize": "",
    "href": "/career",
    "isMobileGame": false,
    "isExternal": false,
    "variant": "",
    "eventLabel": "player-profile",
    "hideOnDesktop": false,
    "hideOnMobile": false,
    "requiresAuthentication": false
  },
  {
    "type": "nav_dropdown",
    "title": "ow2-site - account dropdown",
    "elementID": "blz-nav-account",
    "slot": "account",
    "text": "Account",
    "badge": "",
    "icon": "user",
    "href": "",
    "variant": "",
    "links": [
      {
        "title": "Log In",
        "elementID": "blz-nav-battlenet",
        "slot": "dropdown-primary-menu",
        "blzModalTrigger": "",
        "text": "Log In",
        "subtext": "",
        "badge": "",
        "icon": "battlenet",
        "iconSize": "300",
        "href": "/login",
        "isMobileGame": false,
        "isExternal": false,
        "classes": "button-primary",
        "variant": "button-primary",
        "eventLabel": "Login",
        "ctaPlacement": "",
        "event": "click_login",
        "hideOnDesktop": false,
        "hideOnMobile": false
      },
      {
        "title": "Account Settings",
        "elementID": "blz-nav-settings",
        "slot": "dropdown-primary-menu",
        "blzModalTrigger": "",
        "text": "Account Settings",
        "subtext": "",
        "badge": "",
        "icon": "settings",
        "iconSize": "",
        "href": "https://account.battle.net/",
        "isMobileGame": false,
        "isExternal": false,
        "variant": "",
        "eventLabel": "Account Settings",
        "hideOnDesktop": false,
        "hideOnMobile": false
      },
      {
        "title": "Sign Up",
        "elementID": "blz-nav-sign-up",
        "slot": "dropdown-primary-menu",
        "blzModalTrigger": "",
        "text": "Sign Up",
        "subtext": "",
        "badge": "",
        "icon": "edit",
        "iconSize": "",
        "href": "https://account.battle.net/creation",
        "isMobileGame": false,
        "isExternal": false,
        "variant": "",
        "eventLabel": "Sign up",
        "ctaPlacement": "",
        "event": "click_register",
        "hideOnDesktop": false,
        "hideOnMobile": false
      },
      {
        "title": "Log Out",
        "elementID": "blz-nav-log-out",
        "slot": "dropdown-primary-menu",
        "blzModalTrigger": "",
        "text": "Log Out",
        "subtext": "",
        "badge": "",
        "icon": "log-out",
        "iconSize": "",
        "href": "/logout",
        "isMobileGame": false,
        "isExternal": false,
        "variant": "",
        "eventLabel": "Log out",
        "ctaPlacement": "",
        "event": "click_header_nav",
        "hideOnDesktop": false,
        "hideOnMobile": false
      },
      {
        "title": "Support",
        "elementID": "blz-nav-support",
        "slot": "dropdown-secondary-menu",
        "blzModalTrigger": "",
        "text": "Support",
        "subtext": "",
        "badge": "",
        "icon": "help-circle",
        "iconSize": "",
        "href": "https://battle.net/support/",
        "isMobileGame": false,
        "isExternal": false,
        "variant": "",
        "eventLabel": "Support",
        "hideOnDesktop": false,
        "hideOnMobile": false
      },
      {
        "title": "Shop",
        "elementID": "blz-nav-shop",
        "slot": "dropdown-secondary-menu",
        "blzModalTrigger": "",
        "text": "Shop",
        "subtext": "",
        "badge": "",
        "icon": "shopping-bag",
        "iconSize": "",
        "href": "https://shop.battle.net/",
        "isMobileGame": false,
        "variant": "",
        "eventLabel": "shop"
      },
      {
        "title": "Download Battle.net - Secondary",
        "elementID": "blz-nav-download-bnet-desktop",
        "slot": "dropdown-secondary-menu",
        "blzModalTrigger": "",
        "text": "Download Battle.net",
        "subtext": "",
        "badge": "",
        "icon": "download",
        "iconSize": "",
        "href": "https://www.blizzard.com/download/confirmation?product=bnetdesk",
        "isMobileGame": false,
        "isExternal": false,
        "variant": "",
        "eventLabel": "Battle.net Launcher Download",
        "ctaPlacement": "Navbar - Account Menu",
        "event": "download_launcher",
        "hideOnDesktop": false,
        "hideOnMobile": true
      },
      {
        "title": "Download Battle.net - Mobile",
        "elementID": "blz-nav-download-bnet-mobile",
        "slot": "dropdown-secondary-menu",
        "blzModalTrigger": "",
        "text": "Battle.net Mobile App",
        "subtext": "",
        "badge": "",
        "icon": "phone",
        "iconSize": "",
        "href": "https://www.blizzard.com/apps/battle.net/mobile/",
        "isMobileGame": false,
        "isExternal": false,
        "variant": "",
        "eventLabel": "Battle.net Launcher Download",
        "event": "download_launcher",
        "hideOnDesktop": true,
        "hideOnMobile": false
      }
    ],
    "submenuHeading": "",
    "hideOnDesktop": false,
    "hideOnMobile": false,
    "requiresAuthentication": false
  },
  {
    "type": "nav_link",
    "title": "ow2 - Play Now",
    "elementID": "blz-nav-nav-play-now",
    "slot": "navbar-cta",
    "blzDevice": "",
    "blzModalTrigger": "platform-selection-1",
    "text": "Play Now",
    "subtext": "",
    "badge": "",
    "icon": "",
    "iconSize": "",
    "href": "",
    "isMobileGame": false,
    "isExternal": false,
    "classes": "button-primary",
    "variant": "button-primary",
    "eventLabel": "Play Now",
    "event": "click_download",
    "hideOnDesktop": false,
    "hideOnMobile": false,
    "requiresAuthentication": false
  },
  {
    "type": "base_nav_theme",
    "title": "ow2",
    "tokens": {
      "data": "--navbar-background-color: rgba(229, 235, 244, 0.8); --navbar-background-color-no-blur: rgba(229, 235, 244, 0.95); --navbar-button-color-primary: #f06414; --navbar-button-color-primary-hover: #f1742b; --navbar-button-color-secondary: #05a0fa; --navbar-button-color-secondary-hover: #1ea9fb; --navbar-menu-background-color: #ebeff4; --navbar-content-color-primary: #000000; --navbar-content-color-secondary: #0000007f; --navbar-content-color-tertiary: #0000004c; --navbar-blizzard-logo-background-color: #ffffffb2; --navbar-menu-background-color-alt: #0000000c; --navbar-hover-background-color: #0000000c; --navbar-hover-background-color-alt: #00000019; --navbar-badge-text-color: #ffffff; --navbar-battletag-text-color: #009dff; --navbar-search-background-color: #ffffff;"
    }
  }
]